reach_python/__init__.py
reach_python/client.py
reach_python/consumer/__init__.py
reach_python/consumer/queue_async_client.py
reach_python/http_client/__init__.py
reach_python/http_client/async_http_client.py
reach_python/http_client/creator.py
reach_python/http_client/factory.py
reach_python/http_client/sync_http_client.py
reach_python-1.3.4.dist-info/METADATA
reach_python-1.3.4.dist-info/WHEEL
reach_python-1.3.4.dist-info/RECORD
