Metadata-Version: 2.1
Name: reach-python
Version: 1.3.4
Summary: Reach Python Library
Project-URL: Homepage, https://github.com/lijian418/reach
Classifier: License :: OSI Approved :: MIT License
Classifier: Operating System :: OS Independent
Classifier: Programming Language :: Python :: 3
Requires-Python: >=3.7
Requires-Dist: aio-pika==9.0.5
